allgit.py
allgit-1.0.dist-info/LICENSE
allgit-1.0.dist-info/METADATA
allgit-1.0.dist-info/WHEEL
allgit-1.0.dist-info/entry_points.txt
allgit-1.0.dist-info/top_level.txt
allgit-1.0.dist-info/RECORD
