Metadata-Version: 2.1
Name: allgit
Version: 1.0
Summary: Powerful "git multiplexer" for easily working with many repositories
Home-page: https://github.com/inventhouse/allgit
Author: Benjamin Holt
License: MIT
Keywords: git
Platform: UNKNOWN
Classifier: Development Status :: 5 - Production/Stable
Classifier: Environment :: Console
Classifier: Intended Audience :: Developers
Classifier: Operating System :: Unix
Classifier: License :: OSI Approved :: MIT License
Classifier: Natural Language :: English
Classifier: Programming Language :: Python :: 3.6
Classifier: Topic :: Software Development :: Version Control
